django_translate_po/__init__.py
django_translate_po/app.py
django_translate_po/translate.py
django_translate_po/translator_functions.py
django_translate_po/translators/__init__.py
django_translate_po/translators/base_config.py
django_translate_po/translators/base_translator.py
django_translate_po/translators/aws/__init__.py
django_translate_po/translators/aws/translator.py
django_translate_po/translators/google/__init__.py
django_translate_po/translators/google/translator.py
django_translate_po/utilities/__init__.py
django_translate_po/utilities/constants.py
django_translate_po/utilities/get_text.py
django_translate_po/utilities/match.py
translate_po/__init__.py
translate_po/app.py
translate_po/translate.py
translate_po/translator_functions.py
translate_po/translators/__init__.py
translate_po/translators/base_config.py
translate_po/translators/base_translator.py
translate_po/translators/aws/__init__.py
translate_po/translators/aws/translator.py
translate_po/translators/google/__init__.py
translate_po/translators/google/translator.py
translate_po/utilities/__init__.py
translate_po/utilities/constants.py
translate_po/utilities/get_text.py
translate_po/utilities/match.py
django_translate_po-0.2.1.dist-info/LICENSE
django_translate_po-0.2.1.dist-info/METADATA
django_translate_po-0.2.1.dist-info/WHEEL
django_translate_po-0.2.1.dist-info/entry_points.txt
django_translate_po-0.2.1.dist-info/top_level.txt
django_translate_po-0.2.1.dist-info/RECORD
