Metadata-Version: 2.1
Name: django-translate-po
Version: 0.2.1
Summary: Automatic PO file translator
Home-page: https://github.com/KidoThunder/translate-po
Author: Kido Zhao
Author-email: zgdisgod@hotmail.com
License: UNKNOWN
Project-URL: Source, https://github.com/KidoThunder/translate-po
Project-URL: Documentation, https://github.com/KidoThunder/translate-po/docs/main.html
Project-URL: Author, http://blog.zkido.cc
Keywords: Django po translate automatic google & AWS
Platform: UNKNOWN
Classifier: Development Status :: 3 - Alpha
Classifier: Programming Language :: Python :: 3
Classifier: License :: OSI Approved :: MIT License
Classifier: Operating System :: OS Independent
Classifier: Intended Audience :: Developers
Classifier: Topic :: Software Development :: Internationalization
Requires-Python: >=3.6
License-File: LICENSE
Requires-Dist: polib (>=1.1.0)
Requires-Dist: googletrans (>=3.0.0)
Requires-Dist: django (>=2.1.12)
Requires-Dist: boto3 (>=1.9.245)
Requires-Dist: redis (>=3.5.3)
